charm4py-1.1.dist-info/AUTHORS.md
charm4py-1.1.dist-info/RECORD
charm4py-1.1.dist-info/LICENSE
charm4py-1.1.dist-info/WHEEL
charm4py-1.1.dist-info/entry_points.txt
charm4py-1.1.dist-info/NOTICE
charm4py-1.1.dist-info/top_level.txt
charm4py-1.1.dist-info/METADATA
charmrun/__init__.py
charmrun/start.py
charmrun/charmrun
charm4py/sections.py
charm4py/LICENSE
charm4py/_version.py
charm4py/reduction.py
charm4py/c_object_store.cpython-313-darwin.so
charm4py/c_object_store.cpp
charm4py/charm.py
charm4py/c_object_store.pxd
charm4py/channel.py
charm4py/wait.py
charm4py/__init__.py
charm4py/threads.py
charm4py/interactive.py
charm4py/c_object_store.pyx
charm4py/chare.py
charm4py/libcharm_version
charm4py/pool.py
charm4py/entry_method.py
charm4py/object_store.py
charm4py/charmlib/__init__.py
charm4py/charmlib/charmlib_cython.pyx
charm4py/charmlib/charmlib_cython.cpython-313-darwin.so
charm4py/charmlib/ccharm.pxd
charm4py/charmlib/charmlib_cffi.py
charm4py/charmlib/charmlib_ctypes.py
charm4py/charmlib/charmlib_cffi_build.py
charm4py/.libs/libcharm.dylib
charm4py/ray/__init__.py
charm4py/ray/api.py
