Metadata-Version: 2.1
Name: charm4py
Version: 1.1
Summary: Charm4py Parallel Programming Framework
Author-email: Juan Galvez <jjgalvez@illinois.edu>, Maya Taylor <mayat4@illinois.edu>
Maintainer-email: Maya Taylor <mayat4@illinois.edu>
Project-URL: Documentation, https://charm4py.readthedocs.io
Project-URL: Repository, https://github.com/charmplusplus/charm4py
Keywords: parallel,parallel programming,distributed computing,distributed,hpc,HPC,runtime
Classifier: Intended Audience :: Developers
Classifier: License :: Free for non-commercial use
Classifier: Operating System :: MacOS :: MacOS X
Classifier: Operating System :: POSIX
Classifier: Operating System :: POSIX :: Linux
Classifier: Operating System :: Microsoft :: Windows
Classifier: Programming Language :: Python
Classifier: Programming Language :: Python :: 3
Classifier: Topic :: System :: Distributed Computing
Classifier: Topic :: System :: Clustering
Requires-Python: >=3.7
License-File: LICENSE
License-File: NOTICE
License-File: AUTHORS.md
Requires-Dist: numpy>=1.10.0
Requires-Dist: greenlet>=3.0.0
